spyral_utils-1.2.0.dist-info/METADATA
spyral_utils-1.2.0.dist-info/WHEEL
spyral_utils-1.2.0.dist-info/entry_points.txt
spyral_utils-1.2.0.dist-info/licenses/LICENSE.txt
spyral_utils/__init__.py
spyral_utils/constants.py
spyral_utils/nuclear/__init__.py
spyral_utils/nuclear/amdc_2020.txt
spyral_utils/nuclear/nuclear_map.py
spyral_utils/nuclear/particle_id.py
spyral_utils/nuclear/target.py
spyral_utils/plot/__init__.py
spyral_utils/plot/cut.py
spyral_utils/plot/histogram.py
spyral_utils-1.2.0.dist-info/RECORD
