Metadata-Version: 2.1
Name: spyral-utils
Version: 1.2.0
Summary: A collection of useful utilities for the Spyral analysis framework
Author-Email: Gordon McCann <mccann@frib.msu.edu>, Nathan Turi <turi@frib.msu.edu>
License: GPLv3
Requires-Python: <3.13,>=3.10
Requires-Dist: numpy<2.0,>=1.26.0
Requires-Dist: scipy>=1.11.3
Requires-Dist: polars>=0.19.12
Requires-Dist: pycatima>=1.90
Requires-Dist: shapely>=2.0.2
Requires-Dist: vector>=1.3.0
